bq_schema_policy_tags/__init__.py
bq_schema_policy_tags/bigquery_table.py
bq_schema_policy_tags/dataclass_converter.py
bq_schema_policy_tags/py.typed
bq_schema_policy_tags/row_transformer.py
bq_schema_policy_tags/schema_converter.py
bq_schema_policy_tags/cli/bigquery_connection.py
bq_schema_policy_tags/cli/convert_table.py
bq_schema_policy_tags/cli/migrate_tables.py
bq_schema_policy_tags/migration/__init__.py
bq_schema_policy_tags/migration/models.py
bq_schema_policy_tags/migration/schema_diff.py
bq_schema_policy_tags/migration/table_finder.py
bq_schema_policy_tags/types/__init__.py
bq_schema_policy_tags/types/big_query_field_modes.py
bq_schema_policy_tags/types/big_query_types.py
bq_schema_policy_tags/types/type_mapping.py
bq_schema_policy_tags/types/type_parser.py
bq_schema_policy_tags-0.7.3.dist-info/entry_points.txt
bq_schema_policy_tags-0.7.3.dist-info/WHEEL
bq_schema_policy_tags-0.7.3.dist-info/METADATA
bq_schema_policy_tags-0.7.3.dist-info/RECORD
