Metadata-Version: 2.1
Name: bq-schema-policy-tags
Version: 0.7.3
Summary: Define your BigQuery tables as dataclasses. With this forked library you can also add Policy Tags to your dataclasses to protect your PII data.
Home-page: https://github.com/DVDH0/bq-schema-policy-tags
Author: Davy van der Horst
Requires-Python: >=3.7
Classifier: License :: OSI Approved :: MIT License
Requires-Dist: google-cloud-bigquery>=2,<3
Requires-Dist: dacite==1.5.1
Requires-Dist: invoke==1.4.1 ; extra == "develop"
Requires-Dist: black==22.3.0 ; extra == "test"
Requires-Dist: isort==5.6.4 ; extra == "test"
Requires-Dist: mypy==0.931 ; extra == "test"
Requires-Dist: pylint==2.8.3 ; extra == "test"
Requires-Dist: pytest==7.0.1 ; extra == "test"
Requires-Dist: pytest-cov==3.0.0 ; extra == "test"
Provides-Extra: develop
Provides-Extra: test
